ESResolutionScanner/ESResolutionScanner.py
ESResolutionScanner/__init__.py
esresolutionscanner-1.0.2.dist-info/licenses/LICENSE
esresolutionscanner-1.0.2.dist-info/METADATA
esresolutionscanner-1.0.2.dist-info/WHEEL
esresolutionscanner-1.0.2.dist-info/top_level.txt
esresolutionscanner-1.0.2.dist-info/RECORD
