Metadata-Version: 2.4
Name: ESResolutionScanner
Version: 1.0.2
Summary: A scanner for ES resolutions by country
Author-email: Entente <your.email@example.com>
Project-URL: Homepage, https://github.com/yourusername/ESResolutionScanner
Project-URL: Bug Tracker, https://github.com/yourusername/ESResolutionScanner/issues
Classifier: Programming Language :: Python :: 3
Classifier: License :: OSI Approved :: MIT License
Classifier: Operating System :: OS Independent
Requires-Python: >=3.7
License-File: LICENSE
Requires-Dist: requests>=2.25.0
Dynamic: license-file
